README.md
setup.py
mindset/__init__.py
mindset.egg-info/PKG-INFO
mindset.egg-info/SOURCES.txt
mindset.egg-info/dependency_links.txt
mindset.egg-info/top_level.txt