Metadata-Version: 1.1
Name: mindset
Version: 0.0.1
Summary: Mindset
Home-page: https://github.com/alvations/mindset
Author: UNKNOWN
Author-email: UNKNOWN
License: UNKNOWN
Platform: UNKNOWN
Classifier: Programming Language :: Python :: 3
Classifier: License :: OSI Approved :: MIT License
Classifier: Operating System :: OS Independent
